AUTHORS.rst
CONTRIBUTING.rst
HISTORY.rst
LICENSE
MANIFEST.in
README.rst
setup.cfg
setup.py
morphofit/__init__.py
morphofit/background_estimation.py
morphofit/catalogue_managing.py
morphofit/deprecated_functions.py
morphofit/galfit_stamps_utils.py
morphofit/galfit_utils.py
morphofit/image_utils.py
morphofit/morphofit.py
morphofit/plot_utils.py
morphofit/psf_estimation.py
morphofit/run_sextractor.py
morphofit/utils.py
morphofit.egg-info/PKG-INFO
morphofit.egg-info/SOURCES.txt
morphofit.egg-info/dependency_links.txt
morphofit.egg-info/not-zip-safe
morphofit.egg-info/requires.txt
morphofit.egg-info/top_level.txt
morphofit/deprecated_functions_scripts/__init__.py
morphofit/deprecated_functions_scripts/create_master_dictionary_deprecated.py
morphofit/deprecated_functions_scripts/create_table_for_cutting_regions_deprecated.py
morphofit/deprecated_functions_scripts/create_table_for_galfit_fullimage_deprecated_211213.py
morphofit/deprecated_functions_scripts/create_table_for_galfit_fullimage_jobchainer_deprecated.py
morphofit/deprecated_functions_scripts/create_table_for_galfit_regions_deprecated.py
morphofit/deprecated_functions_scripts/create_table_for_galfit_regions_jobchainer_deprecated.py
morphofit/deprecated_functions_scripts/create_table_for_galfit_stamps_deprecated.py
morphofit/deprecated_functions_scripts/create_table_for_galfit_stamps_deprecated_211213.py
morphofit/deprecated_functions_scripts/create_table_for_galfit_stamps_jobchainer_deprecated.py
morphofit/deprecated_functions_scripts/create_table_for_galfit_stamps_tmp.py
morphofit/deprecated_functions_scripts/create_table_for_masterfullimage_deprecated_211213.py
morphofit/deprecated_functions_scripts/create_table_for_masterregions_deprecated_211213.py
morphofit/deprecated_functions_scripts/create_table_for_masterstamps_deprecated.py
morphofit/deprecated_functions_scripts/create_table_for_masterstamps_deprecated_211213.py
morphofit/deprecated_functions_scripts/create_table_for_psf_images_per_target_deprecated.py
morphofit/deprecated_functions_scripts/create_table_for_sextractor_deprecated.py
morphofit/deprecated_functions_scripts/galfit_stamps_utils_deprecated_211213.py
