Metadata-Version: 2.1
Name: morphofit
Version: 1.1.0
Summary: A Python package for the morphological analysis of galaxies (Tortorelli and Mercurio 2023)
Home-page: https://github.com/torluca/morphofit
Download-URL: https://github.com/torluca/morphofit/archive/refs/tags/v1.1.0.tar.gz
Author: Luca Tortorelli
Author-email: Luca.Tortorelli@physik.lmu.de
License: MIT License
Keywords: morphofit,morphology,galfit
Platform: UNKNOWN
Classifier: Development Status :: 5 - Production/Stable
Classifier: Intended Audience :: Science/Research
Classifier: Intended Audience :: Developers
Classifier: License :: OSI Approved :: MIT License
Classifier: Natural Language :: English
Classifier: Programming Language :: Python :: 3
Classifier: Programming Language :: Python :: 3.10
License-File: LICENSE
